reng.py
reng-1.0.0.dist-info/METADATA
reng-1.0.0.dist-info/WHEEL
reng-1.0.0.dist-info/top_level.txt
reng-1.0.0.dist-info/RECORD
