Metadata-Version: 2.1
Name: reng
Version: 1.0.0
Summary: A Python-based rendering engine.
